COPYING
MANIFEST.in
README.md
setup.py
src/py_import_search.egg-info/PKG-INFO
src/py_import_search.egg-info/SOURCES.txt
src/py_import_search.egg-info/dependency_links.txt
src/py_import_search.egg-info/entry_points.txt
src/py_import_search.egg-info/not-zip-safe
src/py_import_search.egg-info/top_level.txt
src/pyimportsearch/__init__.py