Metadata-Version: 1.1
Name: py-import-search
Version: 0.3
Summary: A small utility for searching your source files for specific imports
Home-page: https://github.com/lnielsen-cern/py-import-search
Author: Lars Holm Nielsen
Author-email: lars.holm.nielsen@cern.ch
License: GPL
Platform: UNKNOWN
Classifier: Development Status :: 3 - Alpha
Classifier: Environment :: Console
Classifier: Intended Audience :: Developers
Classifier: License :: OSI Approved :: GNU General Public License v2 (GPLv2)
Classifier: Programming Language :: Python :: 2.6
Classifier: Programming Language :: Python :: 2.7
Classifier: Topic :: Utilities
Classifier: Topic :: Software Development :: Quality Assurance
